griffon/__init__.py
griffon/cli.py
griffon/exceptions.py
griffon/helpers.py
griffon/output.py
griffon/autocomplete/__init__.py
griffon/commands/__init__.py
griffon/commands/configure.py
griffon/commands/custom_commands.py
griffon/commands/docs.py
griffon/commands/plugin_commands.py
griffon/commands/process.py
griffon/commands/queries.py
griffon/commands/reports.py
griffon/commands/entities/__init__.py
griffon/commands/entities/community_component_registry.py
griffon/commands/entities/corgi.py
griffon/commands/entities/helpers.py
griffon/commands/entities/osidb/__init__.py
griffon/commands/entities/osidb/manage.py
griffon/commands/entities/osidb/trackers.py
griffon/commands/entities/osidb/affects/__init__.py
griffon/commands/entities/osidb/affects/cvss.py
griffon/commands/entities/osidb/flaws/__init__.py
griffon/commands/entities/osidb/flaws/acknowledgments.py
griffon/commands/entities/osidb/flaws/comments.py
griffon/commands/entities/osidb/flaws/cvss.py
griffon/commands/entities/osidb/flaws/package_versions.py
griffon/commands/entities/osidb/flaws/references.py
griffon/commands/plugins/__init__.py
griffon/commands/plugins/bugzilla.py
griffon/commands/plugins/cve_mitre.py
griffon/commands/plugins/cvelib.py
griffon/commands/plugins/example.py
griffon/commands/plugins/fcc.py
griffon/commands/plugins/go_vuln.py
griffon/commands/plugins/osv.py
griffon/commands/plugins/semgrep.py
griffon/services/__init__.py
griffon/services/core_process.py
griffon/services/core_queries.py
griffon/services/core_reports.py
tests/__init__.py
tests/conftest.py
tests/test_cli.py
tests/test_entities.py
tests/test_manage.py
tests/test_plugins.py
tests/test_process.py
tests/test_queries.py
tests/test_reports.py
tests/test_unit.py
griffon-0.6.0.dist-info/LICENSE
griffon-0.6.0.dist-info/METADATA
griffon-0.6.0.dist-info/WHEEL
griffon-0.6.0.dist-info/entry_points.txt
griffon-0.6.0.dist-info/top_level.txt
griffon-0.6.0.dist-info/RECORD
