Metadata-Version: 2.1
Name: griffon
Version: 0.6.0
Summary: Red Hat Product Security CLI
Author: James Fuller (Red Hat Product Security), Jakub Frejlach (Red Hat Product Security)
Maintainer: James Fuller (Red Hat Product Security), Jakub Frejlach (Red Hat Product Security)
License: MIT License
Project-URL: Homepage, https://github.com/RedHatProductSecurity/griffon
Project-URL: Documentation, https://github.com/RedHatProductSecurity/griffon/tree/main/docs
Project-URL: Changelog, https://github.com/RedHatProductSecurity/griffon/blob/main/CHANGELOG.md
Project-URL: Issues, https://github.com/RedHatProductSecurity/griffon/issues
Classifier: Topic :: Security
Classifier: License :: OSI Approved :: MIT License
Classifier: Programming Language :: Python :: 3
Classifier: Programming Language :: Python :: 3.9
Requires-Python: >=3.9
License-File: LICENSE
Requires-Dist: click
Requires-Dist: click-completion
Requires-Dist: packageurl-python
Requires-Dist: rich
Requires-Dist: component-registry-bindings >=1.4.0
Requires-Dist: osidb-bindings >=3.5.1
